{
    "type": "FeatureCollection",
    "metadata": {
        "generated": 1413718074000,
        "url": "http://earthquake.usgs.gov/earthquakes/feed/v1.0/summary/2.5_day.geojson",
        "title": "USGS Magnitude 2.5+ Earthquakes, Past Day",
        "status": 200,
        "api": "1.0.13",
        "count": 39
    },
    "features": [{
        "type": "Feature",
        "properties": {
            "mag": 2.6,
            "place": "4km SSE of Volcano, Hawaii",
            "time": 1413717672500,
            "updated": 1413718050521,
            "tz": -600,
            "url": "http://earthquake.usgs.gov/earthquakes/eventpage/hv60791876",
            "detail": "http://earthquake.usgs.gov/earthquakes/feed/v1.0/detail/hv60791876.geojson",
            "felt": 0,
            "cdi": 1,
            "mmi": null,
            "alert": null,
            "status": "AUTOMATIC",
            "tsunami": null,
            "sig": 104,
            "net": "hv",
            "code": "60791876",
            "ids": ",hv60791876,",
            "sources": ",hv,",
            "types": ",dyfi,general-link,geoserve,nearby-cities,origin,",
            "nst": null,
            "dmin": 0.02694946,
            "rms": 0.29,
            "gap": 118.8,
            "magType": "Ml",
            "type": "earthquake",
            "title": "M 2.6 - 4km SSE of Volcano, Hawaii"
        },
        "geometry": {
            "type": "Point",
            "coordinates": [-155.22, 19.3977, 2.5]
        },
        "id": "hv60791876"
    }, {
        "type": "Feature",
        "properties": {
            "mag": 2.5,
            "place": "5km S of Volcano, Hawaii",
            "time": 1413717619500,
            "updated": 1413717983123,
            "tz": -600,
            "url": "http://earthquake.usgs.gov/earthquakes/eventpage/hv60791871",
            "detail": "http://earthquake.usgs.gov/earthquakes/feed/v1.0/detail/hv60791871.geojson",
            "felt": 0,
            "cdi": 1,
            "mmi": null,
            "alert": null,
            "status": "automatic",
            "tsunami": null,
            "sig": 96,
            "net": "hv",
            "code": "60791871",
            "ids": ",hv60791871,",
            "sources": ",hv,",
            "types": ",dyfi,general-link,geoserve,nearby-cities,origin,",
            "nst": null,
            "dmin": 0.008983153,
            "rms": 0.21,
            "gap": 46.799996256,
            "magType": "ml",
            "type": "earthquake",
            "title": "M 2.5 - 5km S of Volcano, Hawaii"
        },
        "geometry": {
            "type": "Point",
            "coordinates": [-155.2458, 19.3838, 3.2]
        },
        "id": "hv60791871"
    }, {
        "type": "Feature",
        "properties": {
            "mag": 4.5,
            "place": "211km SE of Pondaguitan, Philippines",
            "time": 1413714570290,
            "updated": 1413716205000,
            "tz": 540,
            "url": "http://earthquake.usgs.gov/earthquakes/eventpage/usb000snzg",
            "detail": "http://earthquake.usgs.gov/earthquakes/feed/v1.0/detail/usb000snzg.geojson",
            "felt": 0,
            "cdi": 1,
            "mmi": null,
            "alert": null,
            "status": "reviewed",
            "tsunami": null,
            "sig": 312,
            "net": "us",
            "code": "b000snzg",
            "ids": ",usb000snzg,",
            "sources": ",us,",
            "types": ",cap,dyfi,general-link,geoserve,nearby-cities,origin,phase-data,tectonic-summary,",
            "nst": null,
            "dmin": 2.823,
            "rms": 0.62,
            "gap": 83,
            "magType": "mb",
            "type": "earthquake",
            "title": "M 4.5 - 211km SE of Pondaguitan, Philippines"
        },
        "geometry": {
            "type": "Point",
            "coordinates": [127.5279, 5.0032, 102.21]
        },
        "id": "usb000snzg"
    }, {
        "type": "Feature",
        "properties": {
            "mag": 4.8,
            "place": "299km SE of Lambasa, Fiji",
            "time": 1413711138130,
            "updated": 1413712163000,
            "tz": -720,
            "url": "http://earthquake.usgs.gov/earthquakes/eventpage/usb000snz9",
            "detail": "http://earthquake.usgs.gov/earthquakes/feed/v1.0/detail/usb000snz9.geojson",
            "felt": 0,
            "cdi": 1,
            "mmi": null,
            "alert": null,
            "status": "reviewed",
            "tsunami": null,
            "sig": 354,
            "net": "us",
            "code": "b000snz9",
            "ids": ",usb000snz9,",
            "sources": ",us,",
            "types": ",cap,dyfi,geoserve,nearby-cities,origin,phase-data,tectonic-summary,",
            "nst": null,
            "dmin": 3.509,
            "rms": 0.82,
            "gap": 73,
            "magType": "mb",
            "type": "earthquake",
            "title": "M 4.8 - 299km SE of Lambasa, Fiji"
        },
        "geometry": {
            "type": "Point",
            "coordinates": [-178.2674, -17.9139, 618.2]
        },
        "id": "usb000snz9"
    }, {
        "type": "Feature",
        "properties": {
            "mag": 4.7,
            "place": "Izu Islands, Japan region",
            "time": 1413708677580,
            "updated": 1413712196000,
            "tz": 540,
            "url": "http://earthquake.usgs.gov/earthquakes/eventpage/usb000snz5",
            "detail": "http://earthquake.usgs.gov/earthquakes/feed/v1.0/detail/usb000snz5.geojson",
            "felt": 0,
            "cdi": 1,
            "mmi": null,
            "alert": null,
            "status": "reviewed",
            "tsunami": null,
            "sig": 340,
            "net": "us",
            "code": "b000snz5",
            "ids": ",usb000snz5,",
            "sources": ",us,",
            "types": ",cap,dyfi,general-link,geoserve,nearby-cities,origin,phase-data,tectonic-summary,",
            "nst": null,
            "dmin": 2.857,
            "rms": 0.92,
            "gap": 118,
            "magType": "mb",
            "type": "earthquake",
            "title": "M 4.7 - Izu Islands, Japan region"
        },
        "geometry": {
            "type": "Point",
            "coordinates": [141.9362, 30.8921, 10.85]
        },
        "id": "usb000snz5"
    }, {
        "type": "Feature",
        "properties": {
            "mag": 4.4,
            "place": "131km ESE of Mohean, India",
            "time": 1413708361040,
            "updated": 1413713227000,
            "tz": 360,
            "url": "http://earthquake.usgs.gov/earthquakes/eventpage/usb000snz4",
            "detail": "http://earthquake.usgs.gov/earthquakes/feed/v1.0/detail/usb000snz4.geojson",
            "felt": 0,
            "cdi": 1,
            "mmi": null,
            "alert": null,
            "status": "reviewed",
            "tsunami": null,
            "sig": 298,
            "net": "us",
            "code": "b000snz4",
            "ids": ",usb000snz4,",
            "sources": ",us,",
            "types": ",cap,dyfi,general-link,geoserve,nearby-cities,origin,phase-data,tectonic-summary,",
            "nst": null,
            "dmin": 3.385,
            "rms": 0.45,
            "gap": 179,
            "magType": "mb",
            "type": "earthquake",
            "title": "M 4.4 - 131km ESE of Mohean, India"
        },
        "geometry": {
            "type": "Point",
            "coordinates": [94.4213, 7.5149, 37.93]
        },
        "id": "usb000snz4"
    }, {
        "type": "Feature",
        "properties": {
            "mag": 4,
            "place": "102km NE of Miches, Dominican Republic",
            "time": 1413703139800,
            "updated": 1413706084430,
            "tz": -300,
            "url": "http://earthquake.usgs.gov/earthquakes/eventpage/pr14292000",
            "detail": "http://earthquake.usgs.gov/earthquakes/feed/v1.0/detail/pr14292000.geojson",
            "felt": 0,
            "cdi": 1,
            "mmi": null,
            "alert": null,
            "status": "REVIEWED",
            "tsunami": null,
            "sig": 246,
            "net": "pr",
            "code": "14292000",
            "ids": ",pr14292000,",
            "sources": ",pr,",
            "types": ",cap,dyfi,geoserve,nearby-cities,origin,tectonic-summary,",
            "nst": 23,
            "dmin": 1.54061071,
            "rms": 0.4,
            "gap": 158.4,
            "magType": "Md",
            "type": "earthquake",
            "title": "M 4.0 - 102km NE of Miches, Dominican Republic"
        },
        "geometry": {
            "type": "Point",
            "coordinates": [-68.2755, 19.5508, 103]
        },
        "id": "pr14292000"
    }, {
        "type": "Feature",
        "properties": {
            "mag": 2.9,
            "place": "15km NNE of Charlotte Amalie, U.S. Virgin Islands",
            "time": 1413700694100,
            "updated": 1413708509507,
            "tz": -240,
            "url": "http://earthquake.usgs.gov/earthquakes/eventpage/pr14292002",
            "detail": "http://earthquake.usgs.gov/earthquakes/feed/v1.0/detail/pr14292002.geojson",
            "felt": 0,
            "cdi": 1,
            "mmi": null,
            "alert": null,
            "status": "REVIEWED",
            "tsunami": null,
            "sig": 129,
            "net": "pr",
            "code": "14292002",
            "ids": ",pr14292002,",
            "sources": ",pr,",
            "types": ",cap,dyfi,geoserve,nearby-cities,origin,tectonic-summary,",
            "nst": 7,
            "dmin": 0.26230806,
            "rms": 0.2,
            "gap": 201.6,
            "magType": "Md",
            "type": "earthquake",
            "title": "M 2.9 - 15km NNE of Charlotte Amalie, U.S. Virgin Islands"
        },
        "geometry": {
            "type": "Point",
            "coordinates": [-64.8865, 18.4734, 82]
        },
        "id": "pr14292002"
    }, {
        "type": "Feature",
        "properties": {
            "mag": 4.4,
            "place": "62km S of Baracoa, Cuba",
            "time": 1413696329900,
            "updated": 1413700547000,
            "tz": -300,
            "url": "http://earthquake.usgs.gov/earthquakes/eventpage/usb000snyu",
            "detail": "http://earthquake.usgs.gov/earthquakes/feed/v1.0/detail/usb000snyu.geojson",
            "felt": 0,
            "cdi": 1,
            "mmi": null,
            "alert": null,
            "status": "reviewed",
            "tsunami": null,
            "sig": 298,
            "net": "us",
            "code": "b000snyu",
            "ids": ",usb000snyu,",
            "sources": ",us,",
            "types": ",cap,dyfi,geoserve,nearby-cities,origin,phase-data,tectonic-summary,",
            "nst": null,
            "dmin": 0.631,
            "rms": 0.95,
            "gap": 91,
            "magType": "mb",
            "type": "earthquake",
            "title": "M 4.4 - 62km S of Baracoa, Cuba"
        },
        "geometry": {
            "type": "Point",
            "coordinates": [-74.4571, 19.7859, 13.52]
        },
        "id": "usb000snyu"
    }, {
        "type": "Feature",
        "properties": {
            "mag": 4.8,
            "place": "106km SSE of Akureyri, Iceland",
            "time": 1413688928570,
            "updated": 1413717912183,
            "tz": 0,
            "url": "http://earthquake.usgs.gov/earthquakes/eventpage/usb000snye",
            "detail": "http://earthquake.usgs.gov/earthquakes/feed/v1.0/detail/usb000snye.geojson",
            "felt": null,
            "cdi": null,
            "mmi": null,
            "alert": null,
            "status": "reviewed",
            "tsunami": null,
            "sig": 354,
            "net": "us",
            "code": "b000snye",
            "ids": ",usb000snye,",
            "sources": ",us,",
            "types": ",cap,dyfi,general-link,geoserve,nearby-cities,origin,phase-data,",
            "nst": null,
            "dmin": 1.664,
            "rms": 0.66,
            "gap": 112,
            "magType": "mb",
            "type": "earthquake",
            "title": "M 4.8 - 106km SSE of Akureyri, Iceland"
        },
        "geometry": {
            "type": "Point",
            "coordinates": [-17.4461, 64.7647, 7.45]
        },
        "id": "usb000snye"
    }, {
        "type": "Feature",
        "properties": {
            "mag": 3,
            "place": "14km WSW of Pawnee, Oklahoma",
            "time": 1413687841310,
            "updated": 1413689950772,
            "tz": -300,
            "url": "http://earthquake.usgs.gov/earthquakes/eventpage/usb000sny9",
            "detail": "http://earthquake.usgs.gov/earthquakes/feed/v1.0/detail/usb000sny9.geojson",
            "felt": 3,
            "cdi": 3.4,
            "mmi": null,
            "alert": null,
            "status": "reviewed",
            "tsunami": null,
            "sig": 139,
            "net": "us",
            "code": "b000sny9",
            "ids": ",usb000sny9,",
            "sources": ",us,",
            "types": ",cap,dyfi,general-link,geoserve,nearby-cities,origin,phase-data,tectonic-summary,",
            "nst": null,
            "dmin": 0.224,
            "rms": 0.56,
            "gap": 36,
            "magType": "mb_lg",
            "type": "earthquake",
            "title": "M 3.0 - 14km WSW of Pawnee, Oklahoma"
        },
        "geometry": {
            "type": "Point",
            "coordinates": [-96.9477, 36.2857, 1.57]
        },
        "id": "usb000sny9"
    }, {
        "type": "Feature",
        "properties": {
            "mag": 4.5,
            "place": "3km WSW of La Virginia, Colombia",
            "time": 1413685234190,
            "updated": 1413714198773,
            "tz": -300,
            "url": "http://earthquake.usgs.gov/earthquakes/eventpage/usb000sny7",
            "detail": "http://earthquake.usgs.gov/earthquakes/feed/v1.0/detail/usb000sny7.geojson",
            "felt": null,
            "cdi": null,
            "mmi": null,
            "alert": null,
            "status": "reviewed",
            "tsunami": null,
            "sig": 312,
            "net": "us",
            "code": "b000sny7",
            "ids": ",usb000sny7,",
            "sources": ",us,",
            "types": ",cap,dyfi,general-link,geoserve,nearby-cities,origin,phase-data,tectonic-summary,",
            "nst": null,
            "dmin": 1.588,
            "rms": 1.06,
            "gap": 93,
            "magType": "mb",
            "type": "earthquake",
            "title": "M 4.5 - 3km WSW of La Virginia, Colombia"
        },
        "geometry": {
            "type": "Point",
            "coordinates": [-75.9146, 4.8854, 127.71]
        },
        "id": "usb000sny7"
    }, {
        "type": "Feature",
        "properties": {
            "mag": 3,
            "place": "14km WSW of Pawnee, Oklahoma",
            "time": 1413683384390,
            "updated": 1413690920489,
            "tz": -300,
            "url": "http://earthquake.usgs.gov/earthquakes/eventpage/usb000sny3",
            "detail": "http://earthquake.usgs.gov/earthquakes/feed/v1.0/detail/usb000sny3.geojson",
            "felt": 1,
            "cdi": 1,
            "mmi": null,
            "alert": null,
            "status": "reviewed",
            "tsunami": null,
            "sig": 139,
            "net": "us",
            "code": "b000sny3",
            "ids": ",usb000sny3,",
            "sources": ",us,",
            "types": ",cap,dyfi,general-link,geoserve,nearby-cities,origin,phase-data,tectonic-summary,",
            "nst": null,
            "dmin": 0.226,
            "rms": 0.43,
            "gap": 35,
            "magType": "mb_lg",
            "type": "earthquake",
            "title": "M 3.0 - 14km WSW of Pawnee, Oklahoma"
        },
        "geometry": {
            "type": "Point",
            "coordinates": [-96.9516, 36.2842, 1.24]
        },
        "id": "usb000sny3"
    }, {
        "type": "Feature",
        "properties": {
            "mag": 3.3,
            "place": "12km WSW of Pawnee, Oklahoma",
            "time": 1413681373580,
            "updated": 1413690903571,
            "tz": -300,
            "url": "http://earthquake.usgs.gov/earthquakes/eventpage/usb000snxp",
            "detail": "http://earthquake.usgs.gov/earthquakes/feed/v1.0/detail/usb000snxp.geojson",
            "felt": 8,
            "cdi": 3.4,
            "mmi": null,
            "alert": null,
            "status": "reviewed",
            "tsunami": null,
            "sig": 170,
            "net": "us",
            "code": "b000snxp",
            "ids": ",usb000snxp,",
            "sources": ",us,",
            "types": ",cap,dyfi,general-link,geoserve,nearby-cities,origin,phase-data,tectonic-summary,",
            "nst": null,
            "dmin": 0.215,
            "rms": 0.61,
            "gap": 59,
            "magType": "mb_lg",
            "type": "earthquake",
            "title": "M 3.3 - 12km WSW of Pawnee, Oklahoma"
        },
        "geometry": {
            "type": "Point",
            "coordinates": [-96.9336, 36.2868, 5.73]
        },
        "id": "usb000snxp"
    }, {
        "type": "Feature",
        "properties": {
            "mag": 2.7,
            "place": "72km NNW of Talkeetna, Alaska",
            "time": 1413680309000,
            "updated": 1413709263042,
            "tz": -480,
            "url": "http://earthquake.usgs.gov/earthquakes/eventpage/ak11422600",
            "detail": "http://earthquake.usgs.gov/earthquakes/feed/v1.0/detail/ak11422600.geojson",
            "felt": null,
            "cdi": null,
            "mmi": null,
            "alert": null,
            "status": "automatic",
            "tsunami": null,
            "sig": 112,
            "net": "ak",
            "code": "11422600",
            "ids": ",ak11422600,",
            "sources": ",ak,",
            "types": ",dyfi,general-link,geoserve,nearby-cities,origin,tectonic-summary,",
            "nst": null,
            "dmin": null,
            "rms": 0.68,
            "gap": null,
            "magType": "ml",
            "type": "earthquake",
            "title": "M 2.7 - 72km NNW of Talkeetna, Alaska"
        },
        "geometry": {
            "type": "Point",
            "coordinates": [-150.7645, 62.8984, 110.4]
        },
        "id": "ak11422600"
    }, {
        "type": "Feature",
        "properties": {
            "mag": 4.4,
            "place": "106km W of Banda Aceh, Indonesia",
            "time": 1413678932600,
            "updated": 1413707883756,
            "tz": 360,
            "url": "http://earthquake.usgs.gov/earthquakes/eventpage/usb000snxj",
            "detail": "http://earthquake.usgs.gov/earthquakes/feed/v1.0/detail/usb000snxj.geojson",
            "felt": null,
            "cdi": null,
            "mmi": null,
            "alert": null,
            "status": "reviewed",
            "tsunami": null,
            "sig": 298,
            "net": "us",
            "code": "b000snxj",
            "ids": ",usb000snxj,",
            "sources": ",us,",
            "types": ",cap,dyfi,general-link,geoserve,nearby-cities,origin,phase-data,tectonic-summary,",
            "nst": null,
            "dmin": 2.563,
            "rms": 0.59,
            "gap": 165,
            "magType": "mb",
            "type": "earthquake",
            "title": "M 4.4 - 106km W of Banda Aceh, Indonesia"
        },
        "geometry": {
            "type": "Point",
            "coordinates": [94.3775, 5.3837, 58.98]
        },
        "id": "usb000snxj"
    }, {
        "type": "Feature",
        "properties": {
            "mag": 4.2,
            "place": "121km WSW of Santiago de Cao, Peru",
            "time": 1413673509910,
            "updated": 1413702458953,
            "tz": -300,
            "url": "http://earthquake.usgs.gov/earthquakes/eventpage/usb000snxf",
            "detail": "http://earthquake.usgs.gov/earthquakes/feed/v1.0/detail/usb000snxf.geojson",
            "felt": null,
            "cdi": null,
            "mmi": null,
            "alert": null,
            "status": "reviewed",
            "tsunami": null,
            "sig": 271,
            "net": "us",
            "code": "b000snxf",
            "ids": ",usb000snxf,",
            "sources": ",us,",
            "types": ",cap,dyfi,general-link,geoserve,nearby-cities,origin,phase-data,tectonic-summary,",
            "nst": null,
            "dmin": 4.804,
            "rms": 0.77,
            "gap": 150,
            "magType": "mb",
            "type": "earthquake",
            "title": "M 4.2 - 121km WSW of Santiago de Cao, Peru"
        },
        "geometry": {
            "type": "Point",
            "coordinates": [-80.2093, -8.4866, 35]
        },
        "id": "usb000snxf"
    }, {
        "type": "Feature",
        "properties": {
            "mag": 2.56,
            "place": "24km NE of Soledad, California",
            "time": 1413670873270,
            "updated": 1413685564768,
            "tz": -420,
            "url": "http://earthquake.usgs.gov/earthquakes/eventpage/nc72329916",
            "detail": "http://earthquake.usgs.gov/earthquakes/feed/v1.0/detail/nc72329916.geojson",
            "felt": 2,
            "cdi": 2,
            "mmi": null,
            "alert": null,
            "status": "automatic",
            "tsunami": null,
            "sig": 101,
            "net": "nc",
            "code": "72329916",
            "ids": ",nc72329916,",
            "sources": ",nc,",
            "types": ",dyfi,focal-mechanism,general-link,geoserve,nearby-cities,origin,phase-data,scitech-link,tectonic-summary,",
            "nst": 31,
            "dmin": 0.05796,
            "rms": 0.09,
            "gap": 54,
            "magType": "md",
            "type": "earthquake",
            "title": "M 2.6 - 24km NE of Soledad, California"
        },
        "geometry": {
            "type": "Point",
            "coordinates": [-121.1093369, 36.564167, 3.27]
        },
        "id": "nc72329916"
    }, {
        "type": "Feature",
        "properties": {
            "mag": 4.1,
            "place": "73km W of Sinabang, Indonesia",
            "time": 1413670384220,
            "updated": 1413699332455,
            "tz": 360,
            "url": "http://earthquake.usgs.gov/earthquakes/eventpage/usb000snx1",
            "detail": "http://earthquake.usgs.gov/earthquakes/feed/v1.0/detail/usb000snx1.geojson",
            "felt": null,
            "cdi": null,
            "mmi": null,
            "alert": null,
            "status": "reviewed",
            "tsunami": null,
            "sig": 259,
            "net": "us",
            "code": "b000snx1",
            "ids": ",usb000snx1,",
            "sources": ",us,",
            "types": ",cap,dyfi,general-link,geoserve,nearby-cities,origin,phase-data,tectonic-summary,",
            "nst": null,
            "dmin": 2.18,
            "rms": 0.69,
            "gap": 207,
            "magType": "mb",
            "type": "earthquake",
            "title": "M 4.1 - 73km W of Sinabang, Indonesia"
        },
        "geometry": {
            "type": "Point",
            "coordinates": [95.7199, 2.459, 29.54]
        },
        "id": "usb000snx1"
    }, {
        "type": "Feature",
        "properties": {
            "mag": 4.4,
            "place": "Greenland Sea",
            "time": 1413665549590,
            "updated": 1413694506649,
            "tz": 60,
            "url": "http://earthquake.usgs.gov/earthquakes/eventpage/usb000snwv",
            "detail": "http://earthquake.usgs.gov/earthquakes/feed/v1.0/detail/usb000snwv.geojson",
            "felt": null,
            "cdi": null,
            "mmi": null,
            "alert": null,
            "status": "reviewed",
            "tsunami": null,
            "sig": 298,
            "net": "us",
            "code": "b000snwv",
            "ids": ",usb000snwv,",
            "sources": ",us,",
            "types": ",cap,dyfi,geoserve,nearby-cities,origin,phase-data,",
            "nst": null,
            "dmin": 4.869,
            "rms": 0.7,
            "gap": 112,
            "magType": "mb",
            "type": "earthquake",
            "title": "M 4.4 - Greenland Sea"
        },
        "geometry": {
            "type": "Point",
            "coordinates": [8.2293, 73.7475, 10]
        },
        "id": "usb000snwv"
    }, {
        "type": "Feature",
        "properties": {
            "mag": 4.3,
            "place": "70km ESE of Iwaki, Japan",
            "time": 1413663935360,
            "updated": 1413692898231,
            "tz": 540,
            "url": "http://earthquake.usgs.gov/earthquakes/eventpage/usb000snws",
            "detail": "http://earthquake.usgs.gov/earthquakes/feed/v1.0/detail/usb000snws.geojson",
            "felt": null,
            "cdi": null,
            "mmi": null,
            "alert": null,
            "status": "reviewed",
            "tsunami": null,
            "sig": 284,
            "net": "us",
            "code": "b000snws",
            "ids": ",usb000snws,",
            "sources": ",us,",
            "types": ",cap,dyfi,general-link,geoserve,nearby-cities,origin,phase-data,tectonic-summary,",
            "nst": null,
            "dmin": 1.196,
            "rms": 1.13,
            "gap": 164,
            "magType": "mb",
            "type": "earthquake",
            "title": "M 4.3 - 70km ESE of Iwaki, Japan"
        },
        "geometry": {
            "type": "Point",
            "coordinates": [141.5493, 36.7142, 41.43]
        },
        "id": "usb000snws"
    }, {
        "type": "Feature",
        "properties": {
            "mag": 4.5,
            "place": "124km S of Akureyri, Iceland",
            "time": 1413663427030,
            "updated": 1413692385455,
            "tz": 0,
            "url": "http://earthquake.usgs.gov/earthquakes/eventpage/usb000snwq",
            "detail": "http://earthquake.usgs.gov/earthquakes/feed/v1.0/detail/usb000snwq.geojson",
            "felt": null,
            "cdi": null,
            "mmi": null,
            "alert": null,
            "status": "reviewed",
            "tsunami": null,
            "sig": 312,
            "net": "us",
            "code": "b000snwq",
            "ids": ",usb000snwq,",
            "sources": ",us,",
            "types": ",cap,dyfi,general-link,geoserve,nearby-cities,origin,phase-data,",
            "nst": null,
            "dmin": 1.56,
            "rms": 0.66,
            "gap": 111,
            "magType": "mb",
            "type": "earthquake",
            "title": "M 4.5 - 124km S of Akureyri, Iceland"
        },
        "geometry": {
            "type": "Point",
            "coordinates": [-17.7226, 64.5774, 7.36]
        },
        "id": "usb000snwq"
    }, {
        "type": "Feature",
        "properties": {
            "mag": 2.6,
            "place": "35km SSW of Redoubt Volcano, Alaska",
            "time": 1413661907000,
            "updated": 1413690867276,
            "tz": -480,
            "url": "http://earthquake.usgs.gov/earthquakes/eventpage/ak11422464",
            "detail": "http://earthquake.usgs.gov/earthquakes/feed/v1.0/detail/ak11422464.geojson",
            "felt": null,
            "cdi": null,
            "mmi": null,
            "alert": null,
            "status": "automatic",
            "tsunami": null,
            "sig": 104,
            "net": "ak",
            "code": "11422464",
            "ids": ",ak11422464,",
            "sources": ",ak,",
            "types": ",dyfi,general-link,geoserve,nearby-cities,origin,tectonic-summary,",
            "nst": null,
            "dmin": null,
            "rms": 0.95,
            "gap": null,
            "magType": "ml",
            "type": "earthquake",
            "title": "M 2.6 - 35km SSW of Redoubt Volcano, Alaska"
        },
        "geometry": {
            "type": "Point",
            "coordinates": [-152.9781, 60.1884, 117.2]
        },
        "id": "ak11422464"
    }, {
        "type": "Feature",
        "properties": {
            "mag": 4.6,
            "place": "59km SW of Ndoi Island, Fiji",
            "time": 1413661480660,
            "updated": 1413690426571,
            "tz": -720,
            "url": "http://earthquake.usgs.gov/earthquakes/eventpage/usb000snwh",
            "detail": "http://earthquake.usgs.gov/earthquakes/feed/v1.0/detail/usb000snwh.geojson",
            "felt": null,
            "cdi": null,
            "mmi": null,
            "alert": null,
            "status": "reviewed",
            "tsunami": null,
            "sig": 326,
            "net": "us",
            "code": "b000snwh",
            "ids": ",usb000snwh,",
            "sources": ",us,",
            "types": ",cap,dyfi,geoserve,nearby-cities,origin,phase-data,tectonic-summary,",
            "nst": null,
            "dmin": 4.252,
            "rms": 0.75,
            "gap": 55,
            "magType": "mb",
            "type": "earthquake",
            "title": "M 4.6 - 59km SW of Ndoi Island, Fiji"
        },
        "geometry": {
            "type": "Point",
            "coordinates": [-179.0894, -21.0496, 614.71]
        },
        "id": "usb000snwh"
    }, {
        "type": "Feature",
        "properties": {
            "mag": 3,
            "place": "23km WSW of Perry, Oklahoma",
            "time": 1413660372800,
            "updated": 1413677629649,
            "tz": -300,
            "url": "http://earthquake.usgs.gov/earthquakes/eventpage/usb000snw7",
            "detail": "http://earthquake.usgs.gov/earthquakes/feed/v1.0/detail/usb000snw7.geojson",
            "felt": 1,
            "cdi": 1,
            "mmi": null,
            "alert": null,
            "status": "reviewed",
            "tsunami": null,
            "sig": 139,
            "net": "us",
            "code": "b000snw7",
            "ids": ",usb000snw7,",
            "sources": ",us,",
            "types": ",cap,dyfi,general-link,geoserve,nearby-cities,origin,phase-data,tectonic-summary,",
            "nst": null,
            "dmin": null,
            "rms": 0.66,
            "gap": 46,
            "magType": "ml",
            "type": "earthquake",
            "title": "M 3.0 - 23km WSW of Perry, Oklahoma"
        },
        "geometry": {
            "type": "Point",
            "coordinates": [-97.5263, 36.2015, 0.374]
        },
        "id": "usb000snw7"
    }, {
        "type": "Feature",
        "properties": {
            "mag": 4.5,
            "place": "92km WSW of Puerto Madero, Mexico",
            "time": 1413659635260,
            "updated": 1413688590923,
            "tz": -360,
            "url": "http://earthquake.usgs.gov/earthquakes/eventpage/usb000snw6",
            "detail": "http://earthquake.usgs.gov/earthquakes/feed/v1.0/detail/usb000snw6.geojson",
            "felt": null,
            "cdi": null,
            "mmi": null,
            "alert": null,
            "status": "reviewed",
            "tsunami": null,
            "sig": 312,
            "net": "us",
            "code": "b000snw6",
            "ids": ",usb000snw6,",
            "sources": ",us,",
            "types": ",cap,dyfi,general-link,geoserve,nearby-cities,origin,phase-data,tectonic-summary,",
            "nst": null,
            "dmin": 1.514,
            "rms": 0.84,
            "gap": 161,
            "magType": "mb",
            "type": "earthquake",
            "title": "M 4.5 - 92km WSW of Puerto Madero, Mexico"
        },
        "geometry": {
            "type": "Point",
            "coordinates": [-93.2592, 14.5186, 34.49]
        },
        "id": "usb000snw6"
    }, {
        "type": "Feature",
        "properties": {
            "mag": 2.5,
            "place": "75km NW of Fort Yukon, Alaska",
            "time": 1413659258000,
            "updated": 1413688216544,
            "tz": -480,
            "url": "http://earthquake.usgs.gov/earthquakes/eventpage/ak11422414",
            "detail": "http://earthquake.usgs.gov/earthquakes/feed/v1.0/detail/ak11422414.geojson",
            "felt": null,
            "cdi": null,
            "mmi": null,
            "alert": null,
            "status": "automatic",
            "tsunami": null,
            "sig": 96,
            "net": "ak",
            "code": "11422414",
            "ids": ",ak11422414,",
            "sources": ",ak,",
            "types": ",dyfi,general-link,geoserve,nearby-cities,origin,",
            "nst": null,
            "dmin": null,
            "rms": 0.62,
            "gap": null,
            "magType": "ml",
            "type": "earthquake",
            "title": "M 2.5 - 75km NW of Fort Yukon, Alaska"
        },
        "geometry": {
            "type": "Point",
            "coordinates": [-146.4988, 67.0422, 16.7]
        },
        "id": "ak11422414"
    }, {
        "type": "Feature",
        "properties": {
            "mag": 4.4,
            "place": "25km W of Ndoi Island, Fiji",
            "time": 1413656261950,
            "updated": 1413685216753,
            "tz": -720,
            "url": "http://earthquake.usgs.gov/earthquakes/eventpage/usb000snvr",
            "detail": "http://earthquake.usgs.gov/earthquakes/feed/v1.0/detail/usb000snvr.geojson",
            "felt": null,
            "cdi": null,
            "mmi": null,
            "alert": null,
            "status": "reviewed",
            "tsunami": null,
            "sig": 298,
            "net": "us",
            "code": "b000snvr",
            "ids": ",usb000snvr,",
            "sources": ",us,",
            "types": ",cap,dyfi,geoserve,nearby-cities,origin,phase-data,tectonic-summary,",
            "nst": null,
            "dmin": 4.032,
            "rms": 0.74,
            "gap": 92,
            "magType": "mb",
            "type": "earthquake",
            "title": "M 4.4 - 25km W of Ndoi Island, Fiji"
        },
        "geometry": {
            "type": "Point",
            "coordinates": [-178.9476, -20.628, 637.83]
        },
        "id": "usb000snvr"
    }, {
        "type": "Feature",
        "properties": {
            "mag": 2.86,
            "place": "14km SW of Smith Valley, Nevada",
            "time": 1413655193098,
            "updated": 1413695149422,
            "tz": -420,
            "url": "http://earthquake.usgs.gov/earthquakes/eventpage/nn00464468",
            "detail": "http://earthquake.usgs.gov/earthquakes/feed/v1.0/detail/nn00464468.geojson",
            "felt": 3,
            "cdi": 2,
            "mmi": null,
            "alert": null,
            "status": "reviewed",
            "tsunami": null,
            "sig": 126,
            "net": "nn",
            "code": "00464468",
            "ids": ",nn00464468,usb000snv4,",
            "sources": ",nn,us,",
            "types": ",cap,dyfi,general-link,geoserve,nearby-cities,origin,phase-data,",
            "nst": 27,
            "dmin": 0.181,
            "rms": 0.145,
            "gap": 70.55,
            "magType": "ml",
            "type": "earthquake",
            "title": "M 2.9 - 14km SW of Smith Valley, Nevada"
        },
        "geometry": {
            "type": "Point",
            "coordinates": [-119.4503, 38.6844, 10.9694]
        },
        "id": "nn00464468"
    }, {
        "type": "Feature",
        "properties": {
            "mag": 4.7,
            "place": "125km SE of Kuril'sk, Russia",
            "time": 1413653379590,
            "updated": 1413682332370,
            "tz": 600,
            "url": "http://earthquake.usgs.gov/earthquakes/eventpage/usb000snul",
            "detail": "http://earthquake.usgs.gov/earthquakes/feed/v1.0/detail/usb000snul.geojson",
            "felt": null,
            "cdi": null,
            "mmi": null,
            "alert": null,
            "status": "reviewed",
            "tsunami": null,
            "sig": 340,
            "net": "us",
            "code": "b000snul",
            "ids": ",usb000snul,",
            "sources": ",us,",
            "types": ",cap,dyfi,general-link,geoserve,nearby-cities,origin,phase-data,tectonic-summary,",
            "nst": null,
            "dmin": 4.732,
            "rms": 0.65,
            "gap": 134,
            "magType": "mb",
            "type": "earthquake",
            "title": "M 4.7 - 125km SE of Kuril'sk, Russia"
        },
        "geometry": {
            "type": "Point",
            "coordinates": [149.1609, 44.564, 45.3]
        },
        "id": "usb000snul"
    }, {
        "type": "Feature",
        "properties": {
            "mag": 4.9,
            "place": "52km WSW of Santiago, Peru",
            "time": 1413653040740,
            "updated": 1413681992809,
            "tz": -300,
            "url": "http://earthquake.usgs.gov/earthquakes/eventpage/usb000snup",
            "detail": "http://earthquake.usgs.gov/earthquakes/feed/v1.0/detail/usb000snup.geojson",
            "felt": null,
            "cdi": null,
            "mmi": null,
            "alert": null,
            "status": "reviewed",
            "tsunami": null,
            "sig": 369,
            "net": "us",
            "code": "b000snup",
            "ids": ",usb000snup,",
            "sources": ",us,",
            "types": ",cap,dyfi,general-link,geoserve,nearby-cities,origin,phase-data,tectonic-summary,",
            "nst": null,
            "dmin": 2.468,
            "rms": 0.7,
            "gap": 137,
            "magType": "mb",
            "type": "earthquake",
            "title": "M 4.9 - 52km WSW of Santiago, Peru"
        },
        "geometry": {
            "type": "Point",
            "coordinates": [-76.1558, -14.3777, 4.38]
        },
        "id": "usb000snup"
    }, {
        "type": "Feature",
        "properties": {
            "mag": 5,
            "place": "Prince Edward Islands region",
            "time": 1413653038060,
            "updated": 1413681995934,
            "tz": 120,
            "url": "http://earthquake.usgs.gov/earthquakes/eventpage/usb000snuu",
            "detail": "http://earthquake.usgs.gov/earthquakes/feed/v1.0/detail/usb000snuu.geojson",
            "felt": null,
            "cdi": null,
            "mmi": null,
            "alert": null,
            "status": "reviewed",
            "tsunami": null,
            "sig": 385,
            "net": "us",
            "code": "b000snuu",
            "ids": ",usb000snuu,",
            "sources": ",us,",
            "types": ",cap,dyfi,geoserve,nearby-cities,origin,phase-data,",
            "nst": null,
            "dmin": 17.419,
            "rms": 0.92,
            "gap": 42,
            "magType": "mb",
            "type": "earthquake",
            "title": "M 5.0 - Prince Edward Islands region"
        },
        "geometry": {
            "type": "Point",
            "coordinates": [33.4768, -46.8705, 21.24]
        },
        "id": "usb000snuu"
    }, {
        "type": "Feature",
        "properties": {
            "mag": 4.7,
            "place": "74km SSW of Kokopo, Papua New Guinea",
            "time": 1413650536890,
            "updated": 1413679499496,
            "tz": 600,
            "url": "http://earthquake.usgs.gov/earthquakes/eventpage/usb000snu5",
            "detail": "http://earthquake.usgs.gov/earthquakes/feed/v1.0/detail/usb000snu5.geojson",
            "felt": null,
            "cdi": null,
            "mmi": null,
            "alert": null,
            "status": "reviewed",
            "tsunami": null,
            "sig": 340,
            "net": "us",
            "code": "b000snu5",
            "ids": ",usb000snu5,",
            "sources": ",us,",
            "types": ",cap,dyfi,general-link,geoserve,nearby-cities,origin,phase-data,tectonic-summary,",
            "nst": null,
            "dmin": 0.773,
            "rms": 0.93,
            "gap": 88,
            "magType": "mb",
            "type": "earthquake",
            "title": "M 4.7 - 74km SSW of Kokopo, Papua New Guinea"
        },
        "geometry": {
            "type": "Point",
            "coordinates": [151.9004, -4.924, 78.22]
        },
        "id": "usb000snu5"
    }, {
        "type": "Feature",
        "properties": {
            "mag": 2.62,
            "place": "7km E of East Foothills, California",
            "time": 1413645406140,
            "updated": 1413695949706,
            "tz": -420,
            "url": "http://earthquake.usgs.gov/earthquakes/eventpage/nc72329676",
            "detail": "http://earthquake.usgs.gov/earthquakes/feed/v1.0/detail/nc72329676.geojson",
            "felt": 12,
            "cdi": 2.2,
            "mmi": null,
            "alert": null,
            "status": "automatic",
            "tsunami": null,
            "sig": 108,
            "net": "nc",
            "code": "72329676",
            "ids": ",nc72329676,",
            "sources": ",nc,",
            "types": ",dyfi,focal-mechanism,general-link,geoserve,nearby-cities,origin,phase-data,scitech-link,tectonic-summary,",
            "nst": 61,
            "dmin": 0.02821,
            "rms": 0.04,
            "gap": 35,
            "magType": "md",
            "type": "earthquake",
            "title": "M 2.6 - 7km E of East Foothills, California"
        },
        "geometry": {
            "type": "Point",
            "coordinates": [-121.7334976, 37.3741684, 6.53]
        },
        "id": "nc72329676"
    }, {
        "type": "Feature",
        "properties": {
            "mag": 2.7,
            "place": "134km S of McGrath, Alaska",
            "time": 1413643133000,
            "updated": 1413644865672,
            "tz": -480,
            "url": "http://earthquake.usgs.gov/earthquakes/eventpage/ak11422278",
            "detail": "http://earthquake.usgs.gov/earthquakes/feed/v1.0/detail/ak11422278.geojson",
            "felt": 1,
            "cdi": 2,
            "mmi": null,
            "alert": null,
            "status": "automatic",
            "tsunami": null,
            "sig": 112,
            "net": "ak",
            "code": "11422278",
            "ids": ",ak11422278,",
            "sources": ",ak,",
            "types": ",dyfi,general-link,geoserve,nearby-cities,origin,",
            "nst": null,
            "dmin": null,
            "rms": 0.92,
            "gap": null,
            "magType": "ml",
            "type": "earthquake",
            "title": "M 2.7 - 134km S of McGrath, Alaska"
        },
        "geometry": {
            "type": "Point",
            "coordinates": [-155.5102, 61.7477, 9]
        },
        "id": "ak11422278"
    }, {
        "type": "Feature",
        "properties": {
            "mag": 4.5,
            "place": "131km ESE of Esso, Russia",
            "time": 1413642863020,
            "updated": 1413671814744,
            "tz": 720,
            "url": "http://earthquake.usgs.gov/earthquakes/eventpage/usb000sntd",
            "detail": "http://earthquake.usgs.gov/earthquakes/feed/v1.0/detail/usb000sntd.geojson",
            "felt": null,
            "cdi": null,
            "mmi": null,
            "alert": null,
            "status": "reviewed",
            "tsunami": null,
            "sig": 312,
            "net": "us",
            "code": "b000sntd",
            "ids": ",usb000sntd,",
            "sources": ",us,",
            "types": ",cap,dyfi,general-link,geoserve,nearby-cities,origin,phase-data,tectonic-summary,",
            "nst": null,
            "dmin": 2.646,
            "rms": 0.96,
            "gap": 113,
            "magType": "mb",
            "type": "earthquake",
            "title": "M 4.5 - 131km ESE of Esso, Russia"
        },
        "geometry": {
            "type": "Point",
            "coordinates": [160.5709, 55.4129, 136.35]
        },
        "id": "usb000sntd"
    }, {
        "type": "Feature",
        "properties": {
            "mag": 4.4,
            "place": "77km ENE of Chernabura Island, Alaska",
            "time": 1413639209870,
            "updated": 1413668169899,
            "tz": -660,
            "url": "http://earthquake.usgs.gov/earthquakes/eventpage/usb000snt7",
            "detail": "http://earthquake.usgs.gov/earthquakes/feed/v1.0/detail/usb000snt7.geojson",
            "felt": null,
            "cdi": null,
            "mmi": null,
            "alert": null,
            "status": "reviewed",
            "tsunami": null,
            "sig": 298,
            "net": "us",
            "code": "b000snt7",
            "ids": ",usb000snt7,ak11422222,",
            "sources": ",us,ak,",
            "types": ",cap,dyfi,general-link,geoserve,nearby-cities,origin,phase-data,tectonic-summary,",
            "nst": null,
            "dmin": 0.701,
            "rms": 0.93,
            "gap": 154,
            "magType": "mb",
            "type": "earthquake",
            "title": "M 4.4 - 77km ENE of Chernabura Island, Alaska"
        },
        "geometry": {
            "type": "Point",
            "coordinates": [-158.3988, 54.9704, 18.89]
        },
        "id": "usb000snt7"
    }, {
        "type": "Feature",
        "properties": {
            "mag": 2.9,
            "place": "20km ENE of Mooreland, Oklahoma",
            "time": 1413635664260,
            "updated": 1413636539000,
            "tz": -300,
            "url": "http://earthquake.usgs.gov/earthquakes/eventpage/usb000snt3",
            "detail": "http://earthquake.usgs.gov/earthquakes/feed/v1.0/detail/usb000snt3.geojson",
            "felt": 1,
            "cdi": 2.2,
            "mmi": null,
            "alert": null,
            "status": "reviewed",
            "tsunami": null,
            "sig": 130,
            "net": "us",
            "code": "b000snt3",
            "ids": ",usb000snt3,",
            "sources": ",us,",
            "types": ",cap,dyfi,general-link,geoserve,nearby-cities,origin,phase-data,tectonic-summary,",
            "nst": null,
            "dmin": 0.147,
            "rms": 0.35,
            "gap": 133,
            "magType": "mb_lg",
            "type": "earthquake",
            "title": "M 2.9 - 20km ENE of Mooreland, Oklahoma"
        },
        "geometry": {
            "type": "Point",
            "coordinates": [-99.006, 36.527, 3.03]
        },
        "id": "usb000snt3"
    }, {
        "type": "Feature",
        "properties": {
            "mag": 5,
            "place": "67km N of Bristol Island, South Sandwich Islands",
            "time": 1413634449260,
            "updated": 1413663408769,
            "tz": -120,
            "url": "http://earthquake.usgs.gov/earthquakes/eventpage/usb000snt1",
            "detail": "http://earthquake.usgs.gov/earthquakes/feed/v1.0/detail/usb000snt1.geojson",
            "felt": null,
            "cdi": null,
            "mmi": null,
            "alert": null,
            "status": "reviewed",
            "tsunami": null,
            "sig": 385,
            "net": "us",
            "code": "b000snt1",
            "ids": ",usb000snt1,",
            "sources": ",us,",
            "types": ",cap,dyfi,geoserve,nearby-cities,origin,phase-data,",
            "nst": null,
            "dmin": 6.916,
            "rms": 0.68,
            "gap": 66,
            "magType": "mb",
            "type": "earthquake",
            "title": "M 5.0 - 67km N of Bristol Island, South Sandwich Islands"
        },
        "geometry": {
            "type": "Point",
            "coordinates": [-26.5265, -58.4268, 156.82]
        },
        "id": "usb000snt1"
    }],
    "bbox": [-179.0894, -58.4268, 0.374, 160.5709, 73.7475, 637.83]
}